testzeus_sdk/__init__.py
testzeus_sdk/client.py
testzeus_sdk/managers/__init__.py
testzeus_sdk/managers/agent_configs_manager.py
testzeus_sdk/managers/base.py
testzeus_sdk/managers/environment_manager.py
testzeus_sdk/managers/extension_manager.py
testzeus_sdk/managers/notification_channel_manager.py
testzeus_sdk/managers/tag_manager.py
testzeus_sdk/managers/tags_manager.py
testzeus_sdk/managers/tenant_consumption_logs_manager.py
testzeus_sdk/managers/tenant_consumption_manager.py
testzeus_sdk/managers/tenants_manager.py
testzeus_sdk/managers/test_data_manager.py
testzeus_sdk/managers/test_designs_manager.py
testzeus_sdk/managers/test_device_manager.py
testzeus_sdk/managers/test_manager.py
testzeus_sdk/managers/test_report_dash_run_manager.py
testzeus_sdk/managers/test_report_run_manager.py
testzeus_sdk/managers/test_report_schedule_manager.py
testzeus_sdk/managers/test_run_dash_output_steps_manager.py
testzeus_sdk/managers/test_run_dash_outputs_attachments_manager.py
testzeus_sdk/managers/test_run_dash_outputs_manager.py
testzeus_sdk/managers/test_run_dashs_manager.py
testzeus_sdk/managers/test_run_group_manager.py
testzeus_sdk/managers/test_run_manager.py
testzeus_sdk/managers/test_run_reports_manager.py
testzeus_sdk/managers/test_runs_manager.py
testzeus_sdk/managers/test_runs_stage_manager.py
testzeus_sdk/managers/tests_ai_generator_manager.py
testzeus_sdk/managers/tests_manager.py
testzeus_sdk/managers/users_manager.py
testzeus_sdk/models/__init__.py
testzeus_sdk/models/agent_configs.py
testzeus_sdk/models/base.py
testzeus_sdk/models/environment.py
testzeus_sdk/models/extension.py
testzeus_sdk/models/notification_channel.py
testzeus_sdk/models/tag.py
testzeus_sdk/models/tags.py
testzeus_sdk/models/tenant_consumption.py
testzeus_sdk/models/tenant_consumption_logs.py
testzeus_sdk/models/tenants.py
testzeus_sdk/models/test.py
testzeus_sdk/models/test_data.py
testzeus_sdk/models/test_designs.py
testzeus_sdk/models/test_device.py
testzeus_sdk-0.0.15.dist-info/LICENSE
testzeus_sdk-0.0.15.dist-info/METADATA
testzeus_sdk-0.0.15.dist-info/WHEEL
testzeus_sdk-0.0.15.dist-info/entry_points.txt
testzeus_sdk-0.0.15.dist-info/RECORD
