Metadata-Version: 2.1
Name: testzeus-sdk
Version: 0.0.15
Summary: Python SDK for TestZeus testing platform
Home-page: https://github.com/test-zeus-ai/testzeus-sdk
License: MIT
Author: Shriyansh Agnihotri
Author-email: shriyansh@testzeus.com
Requires-Python: >=3.11
Classifier: License :: OSI Approved :: MIT License
Classifier: Programming Language :: Python :: 3
Classifier: Programming Language :: Python :: 3.11
Requires-Dist: aiohttp (>=3.9.3,<4.0.0)
Requires-Dist: dotenv (>=0.9.9,<0.10.0)
Requires-Dist: pocketbase (>=0.15.0,<0.16.0)
Requires-Dist: python-dotenv (>=1.0.1,<2.0.0)
Requires-Dist: toml (>=0.10.2,<0.11.0)
Project-URL: Repository, https://github.com/test-zeus-ai/testzeus-sdk
